faciem/__init__.py
faciem/main.py
faciem-0.0.1.dist-info/LICENSE
faciem-0.0.1.dist-info/METADATA
faciem-0.0.1.dist-info/WHEEL
faciem-0.0.1.dist-info/top_level.txt
faciem-0.0.1.dist-info/RECORD
